aiocloudflare/__init__.py
aiocloudflare/api/__init__.py
aiocloudflare/api/accounts/__init__.py
aiocloudflare/api/accounts/access/__init__.py
aiocloudflare/api/accounts/access/access.py
aiocloudflare/api/accounts/access/apps/__init__.py
aiocloudflare/api/accounts/access/apps/apps.py
aiocloudflare/api/accounts/access/apps/ca/__init__.py
aiocloudflare/api/accounts/access/apps/ca/ca.py
aiocloudflare/api/accounts/access/apps/policies/__init__.py
aiocloudflare/api/accounts/access/apps/policies/policies.py
aiocloudflare/api/accounts/access/apps/revoke_tokens/__init__.py
aiocloudflare/api/accounts/access/apps/revoke_tokens/revoke_tokens.py
aiocloudflare/api/accounts/access/certificates/__init__.py
aiocloudflare/api/accounts/access/certificates/certificates.py
aiocloudflare/api/accounts/access/groups/__init__.py
aiocloudflare/api/accounts/access/groups/groups.py
aiocloudflare/api/accounts/access/identity_providers/__init__.py
aiocloudflare/api/accounts/access/identity_providers/identity_providers.py
aiocloudflare/api/accounts/access/logs/__init__.py
aiocloudflare/api/accounts/access/logs/access_requests/__init__.py
aiocloudflare/api/accounts/access/logs/access_requests/access_requests.py
aiocloudflare/api/accounts/access/logs/logs.py
aiocloudflare/api/accounts/access/organizations/__init__.py
aiocloudflare/api/accounts/access/organizations/organizations.py
aiocloudflare/api/accounts/access/organizations/revoke_user/__init__.py
aiocloudflare/api/accounts/access/organizations/revoke_user/revoke_user.py
aiocloudflare/api/accounts/access/service_tokens/__init__.py
aiocloudflare/api/accounts/access/service_tokens/service_tokens.py
aiocloudflare/api/accounts/accounts.py
aiocloudflare/api/accounts/addressing/__init__.py
aiocloudflare/api/accounts/addressing/addressing.py
aiocloudflare/api/accounts/addressing/prefixes/__init__.py
aiocloudflare/api/accounts/addressing/prefixes/bgp/__init__.py
aiocloudflare/api/accounts/addressing/prefixes/bgp/bgp.py
aiocloudflare-0.2.1.dist-info/LICENSE.rst
aiocloudflare-0.2.1.dist-info/WHEEL
aiocloudflare-0.2.1.dist-info/METADATA
aiocloudflare-0.2.1.dist-info/RECORD
