Metadata-Version: 2.1
Name: aiocloudflare
Version: 0.2.1
Summary: A Cloudflare API wrapper for Python with asyncio support
Home-page: https://github.com/stewart86/aiocloudflare
License: MIT
Author: Stewart Wong
Author-email: siwei.wong@gmail.com
Requires-Python: >=3.9,<4.0
Classifier: Development Status :: 5 - Production/Stable
Classifier: Intended Audience :: Developers
Classifier: License :: OSI Approved :: MIT License
Classifier: Programming Language :: Python :: 3
Classifier: Programming Language :: Python :: 3.10
Classifier: Programming Language :: Python :: 3.9
Classifier: Topic :: Software Development :: Libraries :: Python Modules
Requires-Dist: httpx (>=0.20.0,<0.21.0)
Requires-Dist: python-dotenv (>=0.19.0,<0.20.0)
Project-URL: Repository, https://github.com/stewart86/aiocloudflare
